MANIFEST.in
README.rst
setup.py
django_payu.egg-info/PKG-INFO
django_payu.egg-info/SOURCES.txt
django_payu.egg-info/dependency_links.txt
django_payu.egg-info/requires.txt
django_payu.egg-info/top_level.txt
payu/__init__.py
payu/admin.py
payu/apps.py
payu/gateway.py
payu/models.py
payu/tests.py
payu/migrations/0001_initial.py
payu/migrations/__init__.py